README.rst
setup.cfg
setup.py
openprocurement_client/__init__.py
openprocurement_client/api_base_client.py
openprocurement_client/client.py
openprocurement_client/contract.py
openprocurement_client/document_service_client.py
openprocurement_client/exceptions.py
openprocurement_client/plan.py
openprocurement_client/sync.py
openprocurement_client/utils.py
openprocurement_client.egg-info/PKG-INFO
openprocurement_client.egg-info/SOURCES.txt
openprocurement_client.egg-info/dependency_links.txt
openprocurement_client.egg-info/entry_points.txt
openprocurement_client.egg-info/not-zip-safe
openprocurement_client.egg-info/requires.txt
openprocurement_client.egg-info/top_level.txt
openprocurement_client/tests/__init__.py
openprocurement_client/tests/_server.py
openprocurement_client/tests/data_dict.py
openprocurement_client/tests/main.py
openprocurement_client/tests/tests.py
openprocurement_client/tests/tests_sync.py
openprocurement_client/tests/tests_utils.py