Metadata-Version: 1.1
Name: openprocurement-client
Version: 2.0.0
Summary: UNKNOWN
Home-page: https://github.com/openprocurement/openprocurement.client.python
Author: Quintagroup, Ltd.
Author-email: info@quintagroup.com
License: Apache Software License 2.0
Platform: UNKNOWN
Classifier: Programming Language :: Python
